{
  "pages": [
    {
      "id": 1,
      "name": "Home",
      "logo": "/images/home.jpg",
      "isSelected": true
    },
    {
      "id": 2,
      "name": "Vision & Mission",
      "logo": "/images/vision.jpg",
      "isSelected": false
    },
    {
      "id": 3,
      "name": "Why Watson",
      "logo": "/images/why.jpg",
      "isSelected": false
    },
    {
      "id": 4,
      "name": "Courses",
      "logo": "/images/courses.jpg",
      "isSelected": false
    },
    {
      "id": 5,
      "name": "Teachers",
      "logo": "/images/teachers.jpg",
      "isSelected": false
    },
    {
      "id": 6,
      "name": "Admissions",
      "logo": "/images/admissions.jpg",
      "isSelected": false
    },
    {
      "id": 7,
      "name": "Contact",
      "logo": "/images/contact.jpg",
      "isSelected": false
    },
    {
      "id": 11,
      "name": "Director's Message",
      "logo": "/images/contact.jpg",
      "isSelected": false
    },
    {
      "id": 12,
      "name": "Professional Developement",
      "logo": "/images/Home/pd.jpg",
      "isSelected": false
    },
    {
      "id": 13,
      "name": "Alternate Education",
      "logo": "/images/Home/ae.jpg",
      "isSelected": false
    },
    {
      "id": 14,
      "name": "Parent Instruction",
      "logo": "/images/Watson/pp.jpg",
      "isSelected": false
    },
    {
      "id": 15,
      "name": "Student Instruction",
      "logo": "/images/Watson/si.jpg",
      "isSelected": false
    },
    {
      "id": 21,
      "name": "Time Table 6th - 7th",
      "logo": "/images/contact.jpg",
      "isSelected": false
    },
    {
      "id": 22,
      "name": "Time Table 8th - 10th",
      "logo": "/images/contact.jpg",
      "isSelected": false
    },
    {
      "id": 23,
      "name": "Time Table 11th - 12th",
      "logo": "/images/contact.jpg",
      "isSelected": false
    },
    {
      "id": 24,
      "name": "Meeting 4 PM - 7 PM",
      "logo": "/images/contact.jpg",
      "isSelected": false
    }
  ],
  "events": [
    {
      "id": 151,
      "title": "Orientation Program 2025 - Karwar Branch",
      "content": "A Warm Welcome to Our New Academic Session! 22nd March 2025 Time: 10:30 am Venue: NCS Audi",
      "bullet1": "Meet our esteemed faculty members",
      "bullet2": "Study materials for the new session",
      "bullet3": "Distribution of uniforms",
      "bullet4": "Prospectus overview",
      "bullet5": "Insights into our upcoming academic session",
      "contact": "WATSON ACADEMY",
      "date": "21 March 2025"
    },
    {
      "id": 312,
      "title": "Orientation Program 2025 - Goa Branch",
      "content": "A Warm Welcome to Our New Academic Session! Date: 23rd March 2025 Time: 11 am Venue: Watson Academy",
      "bullet1": "Study materials for the new session",
      "bullet2": "Distribution of uniforms",
      "bullet3": "Prospectus overview",
      "bullet4": "Insights into our upcoming academic session",
      "bullet5": "Meet our esteemed faculty members",
      "contact": "WATSON ACADEMY",
      "date": "19 March 2025"
    },
    {
      "id": 1,
      "title": "Watson Academy Aspirants",
      "content": "We are excited to announce that our CRASH COURSE for NEET program will commence on 12th March and will run for 50 days.",
      "bullet1": "Regular classes (Physics, Chemistry and Biology)",
      "bullet2": "Alternate day mock tests (25 mock tests in total)",
      "bullet3": "00-hour revision classes covering the entire syllabus",
      "bullet4": "",
      "bullet5": "",
      "contact": "This is a crucial period for your NEET preparation, and we urge every student to make the most of it. Our dedicated faculty and team are committed to supporting and guiding you to achieve your goals.",
      "date": "27 Februray 2025"
    }
  ],
  "selectedEvent": "",
  "headlines": [
    {
      "id": 72,
      "title": "Orientation Program 2025",
      "content": "22nd March 2025 - Karwar and 23rd March 2025 - Goa",
      "bullet1": "Orientation Program for Students and Parents",
      "bullet2": "",
      "bullet3": "",
      "bullet4": "",
      "bullet5": "",
      "contact": "WATSON ACADEMY",
      "date": "21 March 2025"
    },
    {
      "id": 913,
      "title": "Admissions are NOW OPEN",
      "content": "Admissions are NOW OPEN for classes 6th to 12th at Watson Academy!",
      "bullet1": "Join us for the new session starting on 23rd March",
      "bullet2": "Share with friends & family who may be interested",
      "bullet3": "Don't miss this opportunity!",
      "bullet4": "Register now and secure your child's future!",
      "bullet5": "",
      "contact": "Contact us: 9834443445/ 9767940053",
      "date": "16 March 2025"
    },
    {
      "id": 1,
      "title": "Urgently Hiring for a Typist",
      "content": "Watson Academy, Goa is looking for a skilled typist to join our team. Immediate joiners required.",
      "bullet1": "Candidate should have Good typing speed and accuracy",
      "bullet2": "Basic Computer knowledge",
      "bullet3": "Attention to details",
      "bullet4": "Prior experience preferred (not mandatory)",
      "bullet5": "",
      "contact": "Interested candidates, please contact us ASAP on 9767940053",
      "date": "25 Februray 2025"
    }
  ],
  "selectedHeadline": "",
  "courses": [
    {
      "name": "Basic Courses",
      "logo": "/images/Courses/basic.jpg",
      "isSelected": false
    },
    {
      "name": "Silent Features",
      "logo": "/images/Courses/silent.jpg",
      "isSelected": false
    },
    {
      "name": "Special Courses",
      "logo": "/images/Courses/special.jpg",
      "isSelected": false
    }
  ],
  "photos": [
    {
      "id": 82,
      "logo": "/images/Posters/image82.jpg",
      "name": "EVENT 1"
    },
    {
      "id": 443,
      "logo": "/images/Posters/image443.jpg",
      "name": "EVENT 1"
    },
    {
      "id": 4,
      "logo": "/images/Posters/image4.jpg",
      "name": "EVENT 1"
    },
    {
      "id": 3,
      "logo": "/images/Posters/image3.jpg",
      "name": "EVENT 2"
    },
    {
      "id": 2,
      "logo": "/images/Posters/image2.jpg",
      "name": "EVENT 2"
    },
    {
      "id": 1,
      "logo": "/images/Posters/image1.jpg",
      "name": "EVENT 2"
    }
  ],
  "posters": [
    {
      "id": 796,
      "logo": "/images/Posters/image796.jpg",
      "isSelected": false
    },
    {
      "id": 82,
      "logo": "/images/Posters/image82.jpg"
    },
    {
      "id": 443,
      "logo": "/images/Posters/image443.jpg"
    },
    {
      "id": 4,
      "logo": "/images/Posters/image4.jpg"
    },
    {
      "id": 3,
      "logo": "/images/Posters/image3.jpg"
    },
    {
      "id": 2,
      "logo": "/images/Posters/image2.jpg"
    },
    {
      "id": 1,
      "logo": "/images/Posters/image1.jpg"
    }
  ],
  "videos": [
    {
      "id": 2,
      "logo": "/videos/video2.mp4"
    },
    {
      "id": 1,
      "logo": "/videos/video1.mp4"
    }
  ],
  "posts": [
    {
      "id": 11,
      "message": "Regular test and discussion improved me a lot.",
      "by": "Ayush (Class XI)",
      "date": "5 May 2024"
    },
    {
      "id": 10,
      "message": "Watson made our parent active participant in our studies.",
      "by": "Abhishek (Class XII)",
      "date": "25 April 2024"
    },
    {
      "id": 9,
      "message": "Personal attension and 24*7 availability of faculties worked for me.",
      "by": "Kirti (Class IX)",
      "date": "17 Februray 2024"
    },
    {
      "id": 8,
      "message": "We Got everything we asked for. Thank you Watson.",
      "by": "Rohini (Class XII)",
      "date": "13 Februray 2024"
    },
    {
      "id": 7,
      "message": "I never came across a doubt i unsolved for more than 1 year.",
      "by": "Swati (Class XII)",
      "date": "1 January 2024"
    },
    {
      "id": 6,
      "message": "Teaching was such that we visualised everything in class.",
      "by": "Sagarika (Class XII)",
      "date": "1 November 2023"
    },
    {
      "id": 5,
      "message": "I own my success to my parents blessings and highly dedicated faculties of Watson.",
      "by": "Vedang (Class XII)",
      "date": "20 November 2023"
    },
    {
      "id": 4,
      "message": "Concept learning is better experience with Watson.",
      "by": "Abhinav (Class XII)",
      "date": "7 Auguest 2023"
    },
    {
      "id": 3,
      "message": "Guidence and support of Watson harnessed of me.",
      "by": "Shubham (Class XII)",
      "date": "30 Mar 2023"
    },
    {
      "id": 2,
      "message": "Watson gave me world, me and my parents dreamt of.",
      "by": "Akansha (Class XII)",
      "date": "11 January 2023"
    },
    {
      "id": 1,
      "message": "Thanks to Watson Academy for making our journey simple with less Complication in Complicated Subject.",
      "by": "Ankita & Chetna (Class XII)",
      "date": "25 July 2022"
    }
  ],
  "selectedPost": "",
  "enquiries": [],
  "classes": [
    6,
    7,
    8,
    9,
    10,
    11,
    12
  ],
  "subjects": [
    {
      "code": "BIO",
      "name": "Biology"
    },
    {
      "code": "CHE",
      "name": "Chemistry"
    },
    {
      "code": "MAT",
      "name": "Maths"
    },
    {
      "code": "PHY",
      "name": "Physics"
    },
    {
      "code": "SCI",
      "name": "Science"
    },
    {
      "code": "C + T",
      "name": "Class + Test"
    }
  ],
  "timetables": [
    {
      "id": 1,
      "standard": 6,
      "hours": "5:00 PM - 6:00 PM",
      "start": "17",
      "startHour": "00",
      "end": "18",
      "endHour": "00",
      "subjects": [
        "MAT",
        "MAT",
        "MAT",
        "MAT",
        "MAT",
        "MAT",
        "C + T"
      ]
    },
    {
      "id": 2,
      "standard": 6,
      "hours": "6:00 PM - 7:00 PM",
      "start": "18",
      "startHour": "00",
      "end": "19",
      "endHour": "00",
      "subjects": [
        "SCI",
        "SCI",
        "SCI",
        "SCI",
        "SCI",
        "SCI",
        "C + T"
      ]
    },
    {
      "id": 3,
      "standard": 7,
      "hours": "5:00 PM - 6:00 PM",
      "start": "17",
      "startHour": "00",
      "end": "18",
      "endHour": "00",
      "subjects": [
        "MAT",
        "MAT",
        "MAT",
        "MAT",
        "MAT",
        "MAT",
        "C + T"
      ]
    },
    {
      "id": 4,
      "standard": 7,
      "hours": "6:00 PM - 7:00 PM",
      "start": "18",
      "startHour": "00",
      "end": "19",
      "endHour": "00",
      "subjects": [
        "BIO",
        "CHE",
        "PHY",
        "BIO",
        "CHE",
        "PHY",
        "C + T"
      ]
    },
    {
      "id": 5,
      "standard": 8,
      "hours": "5:00 PM - 6:00 PM",
      "start": "17",
      "startHour": "00",
      "end": "18",
      "endHour": "00",
      "subjects": [
        "MAT",
        "MAT",
        "MAT",
        "MAT",
        "MAT",
        "MAT",
        "C + T"
      ]
    },
    {
      "id": 6,
      "standard": 8,
      "hours": "6:00 PM - 7:00 PM",
      "start": "18",
      "startHour": "00",
      "end": "19",
      "endHour": "00",
      "subjects": [
        "SCI",
        "SCI",
        "SCI",
        "SCI",
        "SCI",
        "SCI",
        "C + T"
      ]
    },
    {
      "id": 7,
      "standard": 9,
      "hours": "5:00 PM - 6:00 PM",
      "start": "17",
      "startHour": "00",
      "end": "18",
      "endHour": "00",
      "subjects": [
        "MAT",
        "MAT",
        "MAT",
        "MAT",
        "MAT",
        "MAT",
        "C + T"
      ]
    },
    {
      "id": 8,
      "standard": 9,
      "hours": "6:00 PM - 7:00 PM",
      "start": "18",
      "startHour": "00",
      "end": "19",
      "endHour": "00",
      "subjects": [
        "BIO",
        "CHE",
        "PHY",
        "BIO",
        "CHE",
        "PHY",
        "C + T"
      ]
    },
    {
      "id": 9,
      "standard": 10,
      "hours": "6:00 PM - 7:00 PM",
      "start": "18",
      "startHour": "00",
      "end": "19",
      "endHour": "00",
      "subjects": [
        "BIO",
        "BIO",
        "CHE",
        "CHE",
        "PHY",
        "PHY",
        "C + T"
      ]
    },
    {
      "id": 10,
      "standard": 10,
      "hours": "6:00 PM - 7:00 PM",
      "start": "18",
      "startHour": "00",
      "end": "19",
      "endHour": "00",
      "subjects": [
        "MAT",
        "MAT",
        "MAT",
        "MAT",
        "MAT",
        "MAT",
        "C + T"
      ]
    },
    {
      "id": 11,
      "standard": 11,
      "hours": "6:00 AM - 7:00 AM",
      "start": "06",
      "startHour": "00",
      "end": "07",
      "endHour": "00",
      "subjects": [
        "PHY",
        "CHE",
        "PHY",
        "CHE",
        "PHY",
        "CHE",
        "C + T"
      ]
    },
    {
      "id": 12,
      "standard": 11,
      "hours": "5:00 PM - 7:30 PM",
      "start": "17",
      "startHour": "00",
      "end": "19",
      "endHour": "30",
      "subjects": [
        "MAT",
        "BIO",
        "MAT",
        "BIO",
        "MAT",
        "BIO",
        "C + T"
      ]
    },
    {
      "id": 13,
      "standard": 12,
      "hours": "6:00 AM - 7:00 AM",
      "start": "06",
      "startHour": "00",
      "end": "07",
      "endHour": "00",
      "subjects": [
        "PHY",
        "CHE",
        "PHY",
        "CHE",
        "PHY",
        "CHE",
        "C + T"
      ]
    },
    {
      "id": 14,
      "standard": 12,
      "hours": "5:00 PM - 7:30 PM",
      "start": "17",
      "startHour": "00",
      "end": "19",
      "endHour": "30",
      "subjects": [
        "BIO",
        "MAT",
        "BIO",
        "MAT",
        "BIO",
        "MAT",
        "C + T"
      ]
    }
  ],
  "banner": {
    "isDisplayed": false,
    "message": "",
    "position": ""
  },
  "users": [
    {
      "mobile": "8412011412",
      "email": "monu.bits@gmail.com",
      "firstname": "Naveen",
      "lastname": "Jangir",
      "password": "1111"
    },
    {
      "mobile": "9860950561",
      "email": "sonuv002@gmail.com",
      "firstname": "Ravindra",
      "lastname": "Jangir",
      "password": "2222"
    },
    {
      "mobile": "9784461021",
      "email": "bsjangir@gmail.com",
      "firstname": "Bahadur Singh",
      "lastname": "Jangir",
      "password": "3333"
    },
    {
      "mobile": "9767940053",
      "email": "neetujangir@gmail.com",
      "firstname": "Neetu",
      "lastname": "Jangir",
      "password": "Wats0n@0053"
    }
  ],
  "visitors": [
    "103.197.74.220",
    "42.104.220.97",
    "103.197.75.163",
    "203.99.214.80",
    "152.59.11.123",
    "103.197.75.12",
    "103.197.75.167",
    "152.59.11.10",
    "172.225.186.6",
    "152.59.10.123",
    "152.59.12.87",
    "152.59.11.112",
    "152.59.11.194",
    "152.59.11.96",
    "103.197.75.212",
    "42.104.222.26",
    "42.104.222.50",
    "42.104.222.101",
    "42.104.222.6",
    "42.104.224.40",
    "10.1.1.74",
    "10.1.11.149",
    "10.1.0.10",
    "42.104.222.12",
    "42.104.222.252",
    "10.1.11.144",
    "10.1.11.132",
    "152.59.12.147",
    "49.15.234.10",
    "42.104.220.121",
    "49.15.231.46",
    "43.249.184.81",
    "42.107.86.35",
    "42.107.86.16",
    "103.197.75.178",
    "43.249.184.165",
    "42.104.227.237",
    "42.104.216.49",
    "152.59.11.161",
    "103.186.246.196",
    "43.249.184.220",
    "66.249.66.9",
    "66.249.66.7",
    "152.59.189.39",
    "66.249.66.8",
    "152.59.189.215",
    "152.59.189.87",
    "66.249.66.6",
    "103.197.75.224",
    "66.249.66.5",
    "152.59.102.79",
    "103.167.128.99",
    "223.233.85.107",
    "40.77.190.93",
    "106.193.202.67",
    "66.249.66.4",
    "103.167.129.83",
    "103.197.74.213",
    "66.249.79.5",
    "42.104.228.162",
    "40.77.188.76",
    "66.249.68.70",
    "66.249.79.6",
    "66.249.79.193",
    "66.249.79.7",
    "157.45.242.157",
    "152.59.88.188",
    "52.45.146.35",
    "117.99.246.187",
    "136.232.221.210",
    "66.249.72.128",
    "152.59.86.209",
    "43.247.156.12",
    "152.59.10.64",
    "49.15.233.247",
    "223.184.225.14",
    "157.38.74.104",
    "152.58.70.60",
    "103.197.74.62",
    "152.58.70.0",
    "106.205.190.156",
    "103.59.75.196",
    "160.202.10.156",
    "103.81.36.18",
    "150.107.42.168",
    "40.77.202.76",
    "34.221.109.119",
    "152.57.246.179",
    "106.220.138.164",
    "117.99.249.67",
    "49.15.230.208",
    "103.197.74.54",
    "81.82.127.251",
    "157.49.104.218",
    "157.49.105.185",
    "152.59.10.21",
    "123.6.49.18",
    "152.58.158.190",
    "40.77.190.211",
    "103.197.74.1",
    "152.59.13.100",
    "17.241.219.191",
    "152.57.246.57",
    "103.197.75.84",
    "152.59.10.63",
    "17.246.19.125",
    "14.139.251.152",
    "42.106.21.166",
    "34.123.170.104",
    "27.57.45.73",
    "150.107.42.204",
    "122.180.17.220",
    "103.197.75.143",
    "10.1.11.251",
    "152.59.11.42",
    "152.59.11.135",
    "125.22.214.242",
    "42.108.126.21",
    "49.15.234.71",
    "152.56.134.204",
    "103.197.75.236",
    "49.43.119.154",
    "117.215.249.143",
    "152.59.12.46",
    "40.77.188.39",
    "40.160.16.209",
    "152.59.112.212",
    "157.50.69.28",
    "14.139.119.55",
    "43.225.168.99",
    "152.57.246.6"
  ]
}